mixscatter/__init__.py
mixscatter/core.py
mixscatter/liquidstructure/__init__.py
mixscatter/liquidstructure/liquidstructure.py
mixscatter/mixture/__init__.py
mixscatter/mixture/mixture.py
mixscatter/scatteringmodel/__init__.py
mixscatter/scatteringmodel/scatteringmodel.py
mixscatter-0.2.3.dist-info/LICENSE
mixscatter-0.2.3.dist-info/METADATA
mixscatter-0.2.3.dist-info/WHEEL
mixscatter-0.2.3.dist-info/top_level.txt
mixscatter-0.2.3.dist-info/RECORD
