Metadata-Version: 2.1
Name: mixscatter
Version: 0.2.3
Summary: A versatile tool for calculating scattering functions of particle mixtures, particularly for small-angle scattering (SAS) or static and dynamic light scattering (SLS & DLS) applications.
Author-email: Joel Diaz Maier <joel.diazmaier@gmail.de>
Project-URL: Repository, https://github.com/joelmaier/mixscatter
Project-URL: Documentation, https://joelmaier.github.io/mixscatter
Keywords: scattering,small-angle scattering,SAS,dynamic light scattering,DLS,light scattering,particle analysis,particle mixture,scattering functions,form factors,structure factors,scattering experiments,scientific computing,scientific analysis,scientific visualization,physical chemistry,materials science,research tools,data analysis
Classifier: Programming Language :: Python :: 3
Classifier: License :: OSI Approved :: MIT License
Classifier: Operating System :: POSIX :: Linux
Classifier: Operating System :: MacOS
Classifier: Operating System :: Microsoft :: Windows :: Windows 11
Classifier: Intended Audience :: Science/Research
Classifier: Topic :: Scientific/Engineering
Classifier: Programming Language :: Python
Classifier: Programming Language :: Python :: 3.10
Classifier: Programming Language :: Python :: 3.11
Classifier: Programming Language :: Python :: 3.12
Classifier: Typing :: Typed
Classifier: Development Status :: 4 - Beta
Requires-Python: >=3.10
License-File: LICENSE
Requires-Dist: numpy >=1.26
Requires-Dist: scipy >=1.12
Requires-Dist: typing-extensions >=4.0.0 ; python_version < "3.11"
Provides-Extra: dev
Requires-Dist: mixscatter[docs,example,lint,tests,type-check] ; extra == 'dev'
Requires-Dist: pre-commit ~=3.7 ; extra == 'dev'
Requires-Dist: nox ; extra == 'dev'
Provides-Extra: docs
Requires-Dist: mkdocs-material ~=9.5 ; extra == 'docs'
Requires-Dist: mkdocstrings[python] ~=0.25 ; extra == 'docs'
Provides-Extra: example
Requires-Dist: matplotlib ~=3.8 ; extra == 'example'
Provides-Extra: lint
Requires-Dist: ruff ~=0.4 ; extra == 'lint'
Provides-Extra: tests
Requires-Dist: pytest ~=8.2 ; extra == 'tests'
Requires-Dist: pytest-cov ~=5.0 ; extra == 'tests'
Requires-Dist: pytest-mock ~=3.14 ; extra == 'tests'
Provides-Extra: type-check
Requires-Dist: mypy ~=1.10 ; extra == 'type-check'
Requires-Dist: mypy-einsum ~=1.0 ; extra == 'type-check'
Requires-Dist: types-PyYAML ~=6.0 ; extra == 'type-check'
